{
  "name": "next-forge",
  "image": "mcr.microsoft.com/devcontainers/typescript-node:22",
  "features": {
    "ghcr.io/devcontainers/features/github-cli:1": {}
  },
  "customizations": {
    "vscode": {
      "settings": {
        "editor.defaultFormatter": "biomejs.biome",
        "editor.formatOnSave": true,
        "editor.codeActionsOnSave": {
          "quickfix.biome": "explicit",
          "source.organizeImports.biome": "explicit"
        },
        "typescript.tsdk": "node_modules/typescript/lib",
        "typescript.enablePromptUseWorkspaceTsdk": true
      },
      "extensions": [
        "biomejs.biome",
        "dbaeumer.vscode-eslint",
        "prisma.prisma",
        "bradlc.vscode-tailwindcss",
        "ms-azuretools.vscode-docker",
        "Prisma.prisma"
      ]
    }
  },
  "forwardPorts": [3000, 3001, 3002],
  "postCreateCommand": "corepack enable && pnpm install",
  "remoteUser": "node"
}
